{
  "parent": "minecraft:recipes/root",
  "criteria": {
    "has_lost_souls": {
      "conditions": {
        "items": [
          {
            "items": "soulless:lost_souls"
          }
        ]
      },
      "trigger": "minecraft:inventory_changed"
    },
    "has_the_recipe": {
      "conditions": {
        "recipe": "soulless:ghostpowder_from_lost_souls_sugar_gunpowder_redstone"
      },
      "trigger": "minecraft:recipe_unlocked"
    }
  },
  "requirements": [
    [
      "has_the_recipe",
      "has_lost_souls"
    ]
  ],
  "rewards": {
    "recipes": [
      "soulless:ghostpowder_from_lost_souls_sugar_gunpowder_redstone"
    ]
  }
}